README.md
setup.cfg
setup.py
pyogt/__init__.py
pyogt/ogtdeparture.py
pyogt/ogtrest.py
pyogt/ogtstop.py
pyogt.egg-info/PKG-INFO
pyogt.egg-info/SOURCES.txt
pyogt.egg-info/dependency_links.txt
pyogt.egg-info/top_level.txt